{"metadata": {"dbt_schema_version": "https://schemas.getdbt.com/dbt/run-results/v6.json", "dbt_version": "1.8.3", "generated_at": "2024-07-07T14:02:19.757940Z", "invocation_id": "d240bc83-69a6-4520-85d4-ddc3a59f08ab", "env": {}}, "results": [{"status": "success", "timing": [{"name": "compile", "started_at": "2024-07-07T14:02:19.191613Z", "completed_at": "2024-07-07T14:02:19.196184Z"}, {"name": "execute", "started_at": "2024-07-07T14:02:19.197539Z", "completed_at": "2024-07-07T14:02:19.197558Z"}], "thread_id": "Thread-4", "execution_time": 0.02592182159423828, "adapter_response": {}, "message": null, "failures": null, "unique_id": "model.wwi_analytics.stg_gsheets__city", "compiled": true, "compiled_code": "with \n\ntable_source as (\n  select * from raw.gsheets.city\n),\n\nfinal as (\n\n  select \n    cast(city_id as int) as city_id,\n    city,\n    cast(country_id as int) as country_id,\n    TO_TIMESTAMP(last_update, 'YYYY-MM-DD: HH24:MI:SS') AS last_update_timestamp\n\n  from table_source\n)\n\nselect * from final", "relation_name": "analytics.staging.stg_gsheets__city"}, {"status": "success", "timing": [{"name": "compile", "started_at": "2024-07-07T14:02:19.183627Z", "completed_at": "2024-07-07T14:02:19.196771Z"}, {"name": "execute", "started_at": "2024-07-07T14:02:19.199090Z", "completed_at": "2024-07-07T14:02:19.199098Z"}], "thread_id": "Thread-2", "execution_time": 0.029425859451293945, "adapter_response": {}, "message": null, "failures": null, "unique_id": "model.wwi_analytics.stg_gsheets__address", "compiled": true, "compiled_code": "with\n\ntable_source as (\n  select * from raw.gsheets.address\n),\n\nfinal as (\n\n  select \n    cast(address_id as int) as address_id,\n    address as address,\n    cast(city_id as int) as city_id,\n    cast(postal_code as int) as postal_code,\n    cast(phone as int) as address_number,\n    district,\n    TO_TIMESTAMP(last_update, 'YYYY-MM-DD HH24:MI:SS') AS last_update_timestamp\n\n  from table_source\n)\n\nselect * from final", "relation_name": "analytics.staging.stg_gsheets__address"}, {"status": "success", "timing": [{"name": "compile", "started_at": "2024-07-07T14:02:19.187290Z", "completed_at": "2024-07-07T14:02:19.198449Z"}, {"name": "execute", "started_at": "2024-07-07T14:02:19.200769Z", "completed_at": "2024-07-07T14:02:19.200776Z"}], "thread_id": "Thread-3", "execution_time": 0.03043198585510254, "adapter_response": {}, "message": null, "failures": null, "unique_id": "model.wwi_analytics.stg_gsheets__category", "compiled": true, "compiled_code": "with \n\ntable_source as (\n  select * from raw.gsheets.category\n),\n\nfinal as (\n\n  select \n    cast(category_id as int) as category_id,\n    name as category_name,\n    TO_TIMESTAMP(last_update, 'YYYY-MM-DD HH24:MI:SS') AS last_update_timestamp\n\n  from table_source  \n)\n\nselect * from final", "relation_name": "analytics.staging.stg_gsheets__category"}, {"status": "success", "timing": [{"name": "compile", "started_at": "2024-07-07T14:02:19.173771Z", "completed_at": "2024-07-07T14:02:19.201640Z"}, {"name": "execute", "started_at": "2024-07-07T14:02:19.204696Z", "completed_at": "2024-07-07T14:02:19.204704Z"}], "thread_id": "Thread-1", "execution_time": 0.03630828857421875, "adapter_response": {}, "message": null, "failures": null, "unique_id": "model.wwi_analytics.stg_gsheets__actor", "compiled": true, "compiled_code": "with\n\n  table_source as (\n    select * from raw.gsheets.actor\n  ),\n\n  final as (\n\n    select \n        CAST(actor_id AS int) AS actor_id,\n        CONCAT(first_name, ' ', last_name) AS actor_full_name,\n        TO_TIMESTAMP(last_update, 'YYYY-MM-DD HH24:MI:SS') AS last_update_timestamp\n        \n    from table_source\n  )\n\n  select * from final", "relation_name": "analytics.staging.stg_gsheets__actor"}, {"status": "success", "timing": [{"name": "compile", "started_at": "2024-07-07T14:02:19.208940Z", "completed_at": "2024-07-07T14:02:19.221990Z"}, {"name": "execute", "started_at": "2024-07-07T14:02:19.228683Z", "completed_at": "2024-07-07T14:02:19.228691Z"}], "thread_id": "Thread-4", "execution_time": 0.02547430992126465, "adapter_response": {}, "message": null, "failures": null, "unique_id": "model.wwi_analytics.stg_gsheets__country", "compiled": true, "compiled_code": "with \n\ntable_source as (\n  select * from raw.gsheets.country\n),\n\nfinal as (\n\n  select \n    cast(country_id as int) as country_id,\n    country,\n    to_timestamp(last_update, 'YYYY-MM-DD HH24:MI:SS') as last_update_timestamp\n\n  from table_source\n)\n\nselect * from final", "relation_name": "analytics.staging.stg_gsheets__country"}, {"status": "success", "timing": [{"name": "compile", "started_at": "2024-07-07T14:02:19.217498Z", "completed_at": "2024-07-07T14:02:19.227396Z"}, {"name": "execute", "started_at": "2024-07-07T14:02:19.229717Z", "completed_at": "2024-07-07T14:02:19.229724Z"}], "thread_id": "Thread-3", "execution_time": 0.022931337356567383, "adapter_response": {}, "message": null, "failures": null, "unique_id": "model.wwi_analytics.stg_gsheets__film", "compiled": true, "compiled_code": "with\n\ntable_source as (\n  select * from raw.gsheets.film\n),\n\nfinal as (\n\n  select \n    cast(film_id as int) as film_id,\n    title as film_title,\n    cast(length as int) as film_length,\n    rating as film_rating,\n    fulltext,\n    description as film_description,\n    to_number(rental_rate, 10, 2) as rental_rate,\n    cast(release_year as int) as release_year,\n    cast(rental_duration as int) as rental_duration,\n    to_number(replacement_cost, 10, 2) as replacement_cost,\n    special_features,\n    to_timestamp(last_update, 'YYYY-MM-DD HH24:MI:SS') as last_update_timestamp\n\n  from table_source\n)\n\nselect * from final", "relation_name": "analytics.staging.stg_gsheets__film"}, {"status": "success", "timing": [{"name": "compile", "started_at": "2024-07-07T14:02:19.213886Z", "completed_at": "2024-07-07T14:02:19.228085Z"}, {"name": "execute", "started_at": "2024-07-07T14:02:19.231196Z", "completed_at": "2024-07-07T14:02:19.231203Z"}], "thread_id": "Thread-2", "execution_time": 0.025632619857788086, "adapter_response": {}, "message": null, "failures": null, "unique_id": "model.wwi_analytics.stg_gsheets__customer", "compiled": true, "compiled_code": "with \n\ntable_source as (\n  select * from raw.gsheets.customer\n),\n\nfinal as (\n\n  select \n    cast(customer_id as int) as customer_id,\n    email as customer_email,\n\n    case \n      when active = 1 then 'true'\n      when active = 0 then 'false'\n      else null\n    end as customer_is_active,\n\n    cast(store_id as int) as store_id,\n    concat(first_name, ' ', last_name) as customer_name,\n    cast(address_id as int) as address_id,\n    cast(create_date as date) as create_date,\n    to_timestamp(last_update, 'YYYY-MM-DD HH24:MI:SS') as last_update_timestamp\n  \n  from table_source\n)\n\nselect * from final", "relation_name": "analytics.staging.stg_gsheets__customer"}, {"status": "success", "timing": [{"name": "compile", "started_at": "2024-07-07T14:02:19.222830Z", "completed_at": "2024-07-07T14:02:19.230639Z"}, {"name": "execute", "started_at": "2024-07-07T14:02:19.233677Z", "completed_at": "2024-07-07T14:02:19.233684Z"}], "thread_id": "Thread-1", "execution_time": 0.02062535285949707, "adapter_response": {}, "message": null, "failures": null, "unique_id": "model.wwi_analytics.stg_gsheets__film_actor", "compiled": true, "compiled_code": "with \n\ntable_source as (\n  select * from raw.gsheets.film_actor\n),\n\nfinal as (\n\n  select \n    cast(film_id as int) as film_id,\n    cast(actor_id as int) as actor_id,\n    to_timestamp(last_update, 'YYYY-MM-DD HH24:MI:SS') as last_update_timestamp\n  \n  from table_source\n)\n\nselect * from final", "relation_name": "analytics.staging.stg_gsheets__film_actor"}, {"status": "success", "timing": [{"name": "compile", "started_at": "2024-07-07T14:02:19.240564Z", "completed_at": "2024-07-07T14:02:19.251964Z"}, {"name": "execute", "started_at": "2024-07-07T14:02:19.256841Z", "completed_at": "2024-07-07T14:02:19.256850Z"}], "thread_id": "Thread-4", "execution_time": 0.021581172943115234, "adapter_response": {}, "message": null, "failures": null, "unique_id": "model.wwi_analytics.stg_gsheets__film_category", "compiled": true, "compiled_code": "with \n\ntable_source as (\n  select * from raw.gsheets.film_category\n),\n\nfinal as (\n\n  select \n    cast(film_id as int) as film_id,\n    cast(category_id as int) as category_id,\n    to_timestamp(last_update, 'YYYY-MM-DD HH24:MI:SS') as last_update_timestamp\n\n  from table_source\n)\n\nselect * from final", "relation_name": "analytics.staging.stg_gsheets__film_category"}, {"status": "success", "timing": [{"name": "compile", "started_at": "2024-07-07T14:02:19.244009Z", "completed_at": "2024-07-07T14:02:19.256047Z"}, {"name": "execute", "started_at": "2024-07-07T14:02:19.258503Z", "completed_at": "2024-07-07T14:02:19.258512Z"}], "thread_id": "Thread-3", "execution_time": 0.022495031356811523, "adapter_response": {}, "message": null, "failures": null, "unique_id": "model.wwi_analytics.stg_gsheets__inventory", "compiled": true, "compiled_code": "with\n\ntable_source as (\n  select * from raw.gsheets.inventory\n),\n\nfinal as (\n\n  select \n    cast(inventory_id as int) as inventory_id,\n    cast(film_id as int) as film_id,\n    cast(store_id as int) as store_id,\n    to_timestamp(last_update, 'YYYY-MM-DD HH24:MI:SS') as last_update_timestamp\n\n  from table_source\n)\n\nselect * from final", "relation_name": "analytics.staging.stg_gsheets__inventory"}, {"status": "success", "timing": [{"name": "compile", "started_at": "2024-07-07T14:02:19.248081Z", "completed_at": "2024-07-07T14:02:19.257813Z"}, {"name": "execute", "started_at": "2024-07-07T14:02:19.260761Z", "completed_at": "2024-07-07T14:02:19.260768Z"}], "thread_id": "Thread-2", "execution_time": 0.023341894149780273, "adapter_response": {}, "message": null, "failures": null, "unique_id": "model.wwi_analytics.stg_gsheets__language", "compiled": true, "compiled_code": "with \n\ntable_source as (\n  select * from raw.gsheets.language\n),\n\nfinal as (\n\n  select\n    cast(language_id as int) as language_id,\n    name as language_name,\n    to_timestamp(last_update, 'YYYY-MM-DD HH24:MI:SS') as last_update_timestamp\n\n  from table_source\n)\n\nselect * from final", "relation_name": "analytics.staging.stg_gsheets__language"}, {"status": "success", "timing": [{"name": "compile", "started_at": "2024-07-07T14:02:19.252691Z", "completed_at": "2024-07-07T14:02:19.259396Z"}, {"name": "execute", "started_at": "2024-07-07T14:02:19.262450Z", "completed_at": "2024-07-07T14:02:19.262457Z"}], "thread_id": "Thread-1", "execution_time": 0.023177385330200195, "adapter_response": {}, "message": null, "failures": null, "unique_id": "model.wwi_analytics.stg_gsheets__payment", "compiled": true, "compiled_code": "with \n\ntable_source as (\n  select * from raw.gsheets.payment\n),\n\nfinal as (\n\n  select \n    cast(payment_id as int) as payment_id,\n    cast(staff_id as int) as staff_id,\n    cast(rental_id as int) as rental_id,\n    cast(customer_id as int) as customer_id,\n    to_number(amount, 10, 2) as amount,\n    to_timestamp(payment_date, 'YYYY-MM-DD HH24:MI:SS') as payment_date\n\n  from table_source\n\n)\n\nselect * from final", "relation_name": "analytics.staging.stg_gsheets__payment"}, {"status": "success", "timing": [{"name": "compile", "started_at": "2024-07-07T14:02:19.268793Z", "completed_at": "2024-07-07T14:02:19.281802Z"}, {"name": "execute", "started_at": "2024-07-07T14:02:19.293603Z", "completed_at": "2024-07-07T14:02:19.293615Z"}], "thread_id": "Thread-4", "execution_time": 0.03029656410217285, "adapter_response": {}, "message": null, "failures": null, "unique_id": "model.wwi_analytics.stg_gsheets__rental", "compiled": true, "compiled_code": "with \n\ntable_source as (\n    select * from raw.gsheets.rental\n),\n\nfinal as (\n\n  select \n    cast(rental_id as int) as rental_id,\n    cast(staff_id as int) as staff_id,\n    cast(customer_id as int) as customer_id,\n    to_timestamp(rental_date, 'YYYY-MM-DD HH24:MI:SS') as rental_date,\n    return_date,\n    cast(inventory_id as int) as inventory_id,\n    to_timestamp(last_update, 'YYYY-MM-DD HH24:MI:SS') as last_update_timestamp\n\n  from table_source\n)\n\nselect * from final", "relation_name": "analytics.staging.stg_gsheets__rental"}, {"status": "success", "timing": [{"name": "compile", "started_at": "2024-07-07T14:02:19.274067Z", "completed_at": "2024-07-07T14:02:19.292136Z"}, {"name": "execute", "started_at": "2024-07-07T14:02:19.294666Z", "completed_at": "2024-07-07T14:02:19.294673Z"}], "thread_id": "Thread-3", "execution_time": 0.029986858367919922, "adapter_response": {}, "message": null, "failures": null, "unique_id": "model.wwi_analytics.stg_gsheets__staff", "compiled": true, "compiled_code": "with\n\ntable_source as (\n  select * from raw.gsheets.staff\n),\n\nfinal as (\n\n  select \n    cast(staff_id as int) as staff_id,\n    email,\n    password,\n    concat(first_name, ' ', last_name) as staff_fullname,\n    username,\n    active,\n    picture,\n    cast(store_id as int) as store_id,\n    cast(address_id as int) as address_id,\n    last_update\n\n  from table_source\n)\n\nselect * from final", "relation_name": "analytics.staging.stg_gsheets__staff"}, {"status": "success", "timing": [{"name": "compile", "started_at": "2024-07-07T14:02:19.278312Z", "completed_at": "2024-07-07T14:02:19.293009Z"}, {"name": "execute", "started_at": "2024-07-07T14:02:19.295608Z", "completed_at": "2024-07-07T14:02:19.295615Z"}], "thread_id": "Thread-2", "execution_time": 0.028737306594848633, "adapter_response": {}, "message": null, "failures": null, "unique_id": "model.wwi_analytics.stg_gsheets__store", "compiled": true, "compiled_code": "with \n\ntable_source as (\n  select * from raw.gsheets.store\n),\n\nfinal as (\n\n  select\n    cast(store_id as int) as store_id,\n    cast(manager_staff_id as int) as manager_staff_id,\n    cast(address_id as int) as address_id,\n    to_timestamp(last_update, 'YYYY-MM-DD HH24:MI:SS') as last_update_timestamp\n\n  from table_source\n)\n\nselect * from final", "relation_name": "analytics.staging.stg_gsheets__store"}, {"status": "success", "timing": [{"name": "compile", "started_at": "2024-07-07T14:02:19.282668Z", "completed_at": "2024-07-07T14:02:19.297202Z"}, {"name": "execute", "started_at": "2024-07-07T14:02:19.300438Z", "completed_at": "2024-07-07T14:02:19.300446Z"}], "thread_id": "Thread-1", "execution_time": 0.032370567321777344, "adapter_response": {}, "message": null, "failures": null, "unique_id": "test.wwi_analytics.not_null_stg_gsheets__city_city_id.50c145e7a3", "compiled": true, "compiled_code": "\n    \n    \n\n\n\nselect city_id\nfrom analytics.staging.stg_gsheets__city\nwhere city_id is null\n\n\n", "relation_name": null}, {"status": "success", "timing": [{"name": "compile", "started_at": "2024-07-07T14:02:19.305048Z", "completed_at": "2024-07-07T14:02:19.325543Z"}, {"name": "execute", "started_at": "2024-07-07T14:02:19.332046Z", "completed_at": "2024-07-07T14:02:19.332059Z"}], "thread_id": "Thread-4", "execution_time": 0.0324397087097168, "adapter_response": {}, "message": null, "failures": null, "unique_id": "test.wwi_analytics.unique_stg_gsheets__city_city_id.29aee4f37a", "compiled": true, "compiled_code": "\n    \n    \n\nselect\n    city_id as unique_field,\n    count(*) as n_records\n\nfrom analytics.staging.stg_gsheets__city\nwhere city_id is not null\ngroup by city_id\nhaving count(*) > 1\n\n\n", "relation_name": null}, {"status": "success", "timing": [{"name": "compile", "started_at": "2024-07-07T14:02:19.313290Z", "completed_at": "2024-07-07T14:02:19.326466Z"}, {"name": "execute", "started_at": "2024-07-07T14:02:19.333093Z", "completed_at": "2024-07-07T14:02:19.333100Z"}], "thread_id": "Thread-3", "execution_time": 0.03184628486633301, "adapter_response": {}, "message": null, "failures": null, "unique_id": "test.wwi_analytics.not_null_stg_gsheets__address_address_id.93bf7e9d32", "compiled": true, "compiled_code": "\n    \n    \n\n\n\nselect address_id\nfrom analytics.staging.stg_gsheets__address\nwhere address_id is null\n\n\n", "relation_name": null}, {"status": "success", "timing": [{"name": "compile", "started_at": "2024-07-07T14:02:19.318971Z", "completed_at": "2024-07-07T14:02:19.331421Z"}, {"name": "execute", "started_at": "2024-07-07T14:02:19.334145Z", "completed_at": "2024-07-07T14:02:19.334153Z"}], "thread_id": "Thread-2", "execution_time": 0.03227353096008301, "adapter_response": {}, "message": null, "failures": null, "unique_id": "test.wwi_analytics.relationships_stg_gsheets__address_city_id__city_id__ref_stg_gsheets__city_.e364401e98", "compiled": true, "compiled_code": "\n    \n    \n\nwith child as (\n    select city_id as from_field\n    from analytics.staging.stg_gsheets__address\n    where city_id is not null\n),\n\nparent as (\n    select city_id as to_field\n    from analytics.staging.stg_gsheets__city\n)\n\nselect\n    from_field\n\nfrom child\nleft join parent\n    on child.from_field = parent.to_field\n\nwhere parent.to_field is null\n\n\n", "relation_name": null}, {"status": "success", "timing": [{"name": "compile", "started_at": "2024-07-07T14:02:19.327060Z", "completed_at": "2024-07-07T14:02:19.335822Z"}, {"name": "execute", "started_at": "2024-07-07T14:02:19.338506Z", "completed_at": "2024-07-07T14:02:19.338513Z"}], "thread_id": "Thread-1", "execution_time": 0.026132583618164062, "adapter_response": {}, "message": null, "failures": null, "unique_id": "test.wwi_analytics.unique_stg_gsheets__address_address_id.7605a92ace", "compiled": true, "compiled_code": "\n    \n    \n\nselect\n    address_id as unique_field,\n    count(*) as n_records\n\nfrom analytics.staging.stg_gsheets__address\nwhere address_id is not null\ngroup by address_id\nhaving count(*) > 1\n\n\n", "relation_name": null}, {"status": "success", "timing": [{"name": "compile", "started_at": "2024-07-07T14:02:19.343118Z", "completed_at": "2024-07-07T14:02:19.359463Z"}, {"name": "execute", "started_at": "2024-07-07T14:02:19.365848Z", "completed_at": "2024-07-07T14:02:19.365856Z"}], "thread_id": "Thread-4", "execution_time": 0.028102397918701172, "adapter_response": {}, "message": null, "failures": null, "unique_id": "test.wwi_analytics.not_null_stg_gsheets__category_category_id.d91136548a", "compiled": true, "compiled_code": "\n    \n    \n\n\n\nselect category_id\nfrom analytics.staging.stg_gsheets__category\nwhere category_id is null\n\n\n", "relation_name": null}, {"status": "success", "timing": [{"name": "compile", "started_at": "2024-07-07T14:02:19.348518Z", "completed_at": "2024-07-07T14:02:19.365013Z"}, {"name": "execute", "started_at": "2024-07-07T14:02:19.367475Z", "completed_at": "2024-07-07T14:02:19.367483Z"}], "thread_id": "Thread-3", "execution_time": 0.02819967269897461, "adapter_response": {}, "message": null, "failures": null, "unique_id": "test.wwi_analytics.not_null_stg_gsheets__actor_actor_id.b1be368753", "compiled": true, "compiled_code": "\n    \n    \n\n\n\nselect actor_id\nfrom analytics.staging.stg_gsheets__actor\nwhere actor_id is null\n\n\n", "relation_name": null}, {"status": "success", "timing": [{"name": "compile", "started_at": "2024-07-07T14:02:19.353026Z", "completed_at": "2024-07-07T14:02:19.366746Z"}, {"name": "execute", "started_at": "2024-07-07T14:02:19.369131Z", "completed_at": "2024-07-07T14:02:19.369141Z"}], "thread_id": "Thread-2", "execution_time": 0.02926182746887207, "adapter_response": {}, "message": null, "failures": null, "unique_id": "test.wwi_analytics.unique_stg_gsheets__actor_actor_id.4adc7f0874", "compiled": true, "compiled_code": "\n    \n    \n\nselect\n    actor_id as unique_field,\n    count(*) as n_records\n\nfrom analytics.staging.stg_gsheets__actor\nwhere actor_id is not null\ngroup by actor_id\nhaving count(*) > 1\n\n\n", "relation_name": null}, {"status": "success", "timing": [{"name": "compile", "started_at": "2024-07-07T14:02:19.360345Z", "completed_at": "2024-07-07T14:02:19.371095Z"}, {"name": "execute", "started_at": "2024-07-07T14:02:19.373680Z", "completed_at": "2024-07-07T14:02:19.373687Z"}], "thread_id": "Thread-1", "execution_time": 0.026040077209472656, "adapter_response": {}, "message": null, "failures": null, "unique_id": "model.wwi_analytics.dim_address", "compiled": true, "compiled_code": "with\n\naddress as (\n  select * from analytics.staging.stg_gsheets__address\n),\n\ncity as (\n  select * from analytics.staging.stg_gsheets__city\n),\n\ncountry as (\n  select * from analytics.staging.stg_gsheets__country\n),\n\nfinal as (\n\n  select\n    md5(cast(coalesce(cast(address.address_id as TEXT), '_dbt_utils_surrogate_key_null_') as TEXT)) as address_key,\n\n    address.address_id,\n    address.address,\n    address.postal_code,\n    address.address_number,\n    address.district,\n\n    city.city,\n    country.country\n\n  from address\n\n  left join city \n    on address.city_id = city.city_id\n  left join country \n    on city.country_id = country.country_id\n\n)\n\nselect * from final", "relation_name": "analytics.warehouse.dim_address"}, {"status": "success", "timing": [{"name": "compile", "started_at": "2024-07-07T14:02:19.377066Z", "completed_at": "2024-07-07T14:02:19.393948Z"}, {"name": "execute", "started_at": "2024-07-07T14:02:19.461136Z", "completed_at": "2024-07-07T14:02:19.461151Z"}], "thread_id": "Thread-4", "execution_time": 0.08966779708862305, "adapter_response": {}, "message": null, "failures": null, "unique_id": "test.wwi_analytics.not_null_stg_gsheets__country_country_id.b54083ef95", "compiled": true, "compiled_code": "\n    \n    \n\n\n\nselect country_id\nfrom analytics.staging.stg_gsheets__country\nwhere country_id is null\n\n\n", "relation_name": null}, {"status": "success", "timing": [{"name": "compile", "started_at": "2024-07-07T14:02:19.382227Z", "completed_at": "2024-07-07T14:02:19.394654Z"}, {"name": "execute", "started_at": "2024-07-07T14:02:19.462170Z", "completed_at": "2024-07-07T14:02:19.462178Z"}], "thread_id": "Thread-3", "execution_time": 0.08928847312927246, "adapter_response": {}, "message": null, "failures": null, "unique_id": "test.wwi_analytics.relationships_stg_gsheets__city_country_id__country_id__ref_stg_gsheets__country_.acc5a56c3e", "compiled": true, "compiled_code": "\n    \n    \n\nwith child as (\n    select country_id as from_field\n    from analytics.staging.stg_gsheets__city\n    where country_id is not null\n),\n\nparent as (\n    select country_id as to_field\n    from analytics.staging.stg_gsheets__country\n)\n\nselect\n    from_field\n\nfrom child\nleft join parent\n    on child.from_field = parent.to_field\n\nwhere parent.to_field is null\n\n\n", "relation_name": null}, {"status": "success", "timing": [{"name": "compile", "started_at": "2024-07-07T14:02:19.388551Z", "completed_at": "2024-07-07T14:02:19.460554Z"}, {"name": "execute", "started_at": "2024-07-07T14:02:19.463219Z", "completed_at": "2024-07-07T14:02:19.463229Z"}], "thread_id": "Thread-2", "execution_time": 0.08819150924682617, "adapter_response": {}, "message": null, "failures": null, "unique_id": "test.wwi_analytics.unique_stg_gsheets__country_country_id.4f416fb24f", "compiled": true, "compiled_code": "\n    \n    \n\nselect\n    country_id as unique_field,\n    count(*) as n_records\n\nfrom analytics.staging.stg_gsheets__country\nwhere country_id is not null\ngroup by country_id\nhaving count(*) > 1\n\n\n", "relation_name": null}, {"status": "success", "timing": [{"name": "compile", "started_at": "2024-07-07T14:02:19.395259Z", "completed_at": "2024-07-07T14:02:19.464135Z"}, {"name": "execute", "started_at": "2024-07-07T14:02:19.466858Z", "completed_at": "2024-07-07T14:02:19.466865Z"}], "thread_id": "Thread-1", "execution_time": 0.07916903495788574, "adapter_response": {}, "message": null, "failures": null, "unique_id": "test.wwi_analytics.not_null_stg_gsheets__film_film_id.674606a254", "compiled": true, "compiled_code": "\n    \n    \n\n\n\nselect film_id\nfrom analytics.staging.stg_gsheets__film\nwhere film_id is null\n\n\n", "relation_name": null}, {"status": "success", "timing": [{"name": "compile", "started_at": "2024-07-07T14:02:19.477735Z", "completed_at": "2024-07-07T14:02:19.488521Z"}, {"name": "execute", "started_at": "2024-07-07T14:02:19.494445Z", "completed_at": "2024-07-07T14:02:19.494454Z"}], "thread_id": "Thread-3", "execution_time": 0.02613973617553711, "adapter_response": {}, "message": null, "failures": null, "unique_id": "model.wwi_analytics.dim_customer", "compiled": true, "compiled_code": "with \n\ncustomer  as (\n  select * from analytics.staging.stg_gsheets__customer\n),\n\naddress as (\n  select * from analytics.staging.stg_gsheets__address\n),\n\ncity as (\n  select * from analytics.staging.stg_gsheets__city\n),\n\ncountry as (\n  select * from analytics.staging.stg_gsheets__country\n),\n\nfinal as (\n\n  select \n    md5(cast(coalesce(cast(customer.customer_id as TEXT), '_dbt_utils_surrogate_key_null_') as TEXT)) as customer_key,\n\n    customer.customer_id,\n    customer.customer_email,\n    customer.customer_name,\n    customer.customer_is_active,\n\n    address.address,\n    address.postal_code,\n    address.address_number,\n    address.district,\n\n    city.city,\n    country.country\n\n  from customer\n  \n  left join address \n    on customer.address_id = address.address_id\n  left join city \n    on address.city_id = city.city_id\n  left join country \n    on city.country_id = country.country_id\n\n)\n\nselect * from final", "relation_name": "analytics.warehouse.dim_customer"}, {"status": "success", "timing": [{"name": "compile", "started_at": "2024-07-07T14:02:19.482853Z", "completed_at": "2024-07-07T14:02:19.497875Z"}, {"name": "execute", "started_at": "2024-07-07T14:02:19.504956Z", "completed_at": "2024-07-07T14:02:19.504966Z"}], "thread_id": "Thread-2", "execution_time": 0.03602004051208496, "adapter_response": {}, "message": null, "failures": null, "unique_id": "test.wwi_analytics.not_null_stg_gsheets__customer_customer_id.d1c343ea4e", "compiled": true, "compiled_code": "\n    \n    \n\n\n\nselect customer_id\nfrom analytics.staging.stg_gsheets__customer\nwhere customer_id is null\n\n\n", "relation_name": null}, {"status": "success", "timing": [{"name": "compile", "started_at": "2024-07-07T14:02:19.472883Z", "completed_at": "2024-07-07T14:02:19.498480Z"}, {"name": "execute", "started_at": "2024-07-07T14:02:19.506482Z", "completed_at": "2024-07-07T14:02:19.506491Z"}], "thread_id": "Thread-4", "execution_time": 0.03884077072143555, "adapter_response": {}, "message": null, "failures": null, "unique_id": "test.wwi_analytics.unique_stg_gsheets__film_film_id.278bcbdacc", "compiled": true, "compiled_code": "\n    \n    \n\nselect\n    film_id as unique_field,\n    count(*) as n_records\n\nfrom analytics.staging.stg_gsheets__film\nwhere film_id is not null\ngroup by film_id\nhaving count(*) > 1\n\n\n", "relation_name": null}, {"status": "success", "timing": [{"name": "compile", "started_at": "2024-07-07T14:02:19.489219Z", "completed_at": "2024-07-07T14:02:19.505889Z"}, {"name": "execute", "started_at": "2024-07-07T14:02:19.508814Z", "completed_at": "2024-07-07T14:02:19.508821Z"}], "thread_id": "Thread-1", "execution_time": 0.03668999671936035, "adapter_response": {}, "message": null, "failures": null, "unique_id": "test.wwi_analytics.relationships_stg_gsheets__customer_address_id__address_id__ref_stg_gsheets__address_.2fde2b866d", "compiled": true, "compiled_code": "\n    \n    \n\nwith child as (\n    select address_id as from_field\n    from analytics.staging.stg_gsheets__customer\n    where address_id is not null\n),\n\nparent as (\n    select address_id as to_field\n    from analytics.staging.stg_gsheets__address\n)\n\nselect\n    from_field\n\nfrom child\nleft join parent\n    on child.from_field = parent.to_field\n\nwhere parent.to_field is null\n\n\n", "relation_name": null}, {"status": "success", "timing": [{"name": "compile", "started_at": "2024-07-07T14:02:19.499068Z", "completed_at": "2024-07-07T14:02:19.508255Z"}, {"name": "execute", "started_at": "2024-07-07T14:02:19.511079Z", "completed_at": "2024-07-07T14:02:19.511086Z"}], "thread_id": "Thread-3", "execution_time": 0.015127897262573242, "adapter_response": {}, "message": null, "failures": null, "unique_id": "test.wwi_analytics.unique_stg_gsheets__customer_customer_id.1f2d787560", "compiled": true, "compiled_code": "\n    \n    \n\nselect\n    customer_id as unique_field,\n    count(*) as n_records\n\nfrom analytics.staging.stg_gsheets__customer\nwhere customer_id is not null\ngroup by customer_id\nhaving count(*) > 1\n\n\n", "relation_name": null}, {"status": "success", "timing": [{"name": "compile", "started_at": "2024-07-07T14:02:19.515830Z", "completed_at": "2024-07-07T14:02:19.527202Z"}, {"name": "execute", "started_at": "2024-07-07T14:02:19.538891Z", "completed_at": "2024-07-07T14:02:19.538900Z"}], "thread_id": "Thread-2", "execution_time": 0.028560638427734375, "adapter_response": {}, "message": null, "failures": null, "unique_id": "model.wwi_analytics.dim_film", "compiled": true, "compiled_code": "with\n\nfilm_actor as (\n  select * from analytics.staging.stg_gsheets__film_actor\n),\n\nfilm as (\n  select * from analytics.staging.stg_gsheets__film\n),\n\nactor as (\n  select * from analytics.staging.stg_gsheets__actor\n),\n\nfinal as (\n\n  select\n    md5(cast(coalesce(cast(film.film_id as TEXT), '_dbt_utils_surrogate_key_null_') as TEXT)) as film_key, \n\n    film.film_id,\n    film.film_title,\n    film.film_description,\n    film.film_length,\n    film.film_rating,\n    film.release_year,\n    film.rental_rate,\n    film.rental_duration,\n    film.replacement_cost,\n\n    actor.actor_full_name\n\n  from film_actor\n\n  left join film \n    on film_actor.film_id = film.film_id\n  left join actor \n    on film_actor.actor_id = actor.actor_id\n\n)\n\nselect * from final", "relation_name": "analytics.warehouse.dim_film"}, {"status": "success", "timing": [{"name": "compile", "started_at": "2024-07-07T14:02:19.521977Z", "completed_at": "2024-07-07T14:02:19.538293Z"}, {"name": "execute", "started_at": "2024-07-07T14:02:19.540083Z", "completed_at": "2024-07-07T14:02:19.540093Z"}], "thread_id": "Thread-4", "execution_time": 0.027570486068725586, "adapter_response": {}, "message": null, "failures": null, "unique_id": "test.wwi_analytics.not_null_stg_gsheets__film_category_category_id.ed610517ff", "compiled": true, "compiled_code": "\n    \n    \n\n\n\nselect category_id\nfrom analytics.staging.stg_gsheets__film_category\nwhere category_id is null\n\n\n", "relation_name": null}, {"status": "success", "timing": [{"name": "compile", "started_at": "2024-07-07T14:02:19.533618Z", "completed_at": "2024-07-07T14:02:19.541218Z"}, {"name": "execute", "started_at": "2024-07-07T14:02:19.543798Z", "completed_at": "2024-07-07T14:02:19.543805Z"}], "thread_id": "Thread-3", "execution_time": 0.02331376075744629, "adapter_response": {}, "message": null, "failures": null, "unique_id": "test.wwi_analytics.not_null_stg_gsheets__inventory_inventory_id.1cf701ce3d", "compiled": true, "compiled_code": "\n    \n    \n\n\n\nselect inventory_id\nfrom analytics.staging.stg_gsheets__inventory\nwhere inventory_id is null\n\n\n", "relation_name": null}, {"status": "success", "timing": [{"name": "compile", "started_at": "2024-07-07T14:02:19.527813Z", "completed_at": "2024-07-07T14:02:19.541775Z"}, {"name": "execute", "started_at": "2024-07-07T14:02:19.544695Z", "completed_at": "2024-07-07T14:02:19.544705Z"}], "thread_id": "Thread-1", "execution_time": 0.03020620346069336, "adapter_response": {}, "message": null, "failures": null, "unique_id": "test.wwi_analytics.relationships_stg_gsheets__film_category_film_id__film_id__ref_stg_gsheets__film_.b01cd69bc5", "compiled": true, "compiled_code": "\n    \n    \n\nwith child as (\n    select film_id as from_field\n    from analytics.staging.stg_gsheets__film_category\n    where film_id is not null\n),\n\nparent as (\n    select film_id as to_field\n    from analytics.staging.stg_gsheets__film\n)\n\nselect\n    from_field\n\nfrom child\nleft join parent\n    on child.from_field = parent.to_field\n\nwhere parent.to_field is null\n\n\n", "relation_name": null}, {"status": "success", "timing": [{"name": "compile", "started_at": "2024-07-07T14:02:19.557809Z", "completed_at": "2024-07-07T14:02:19.568346Z"}, {"name": "execute", "started_at": "2024-07-07T14:02:19.574210Z", "completed_at": "2024-07-07T14:02:19.574219Z"}], "thread_id": "Thread-4", "execution_time": 0.028049468994140625, "adapter_response": {}, "message": null, "failures": null, "unique_id": "test.wwi_analytics.unique_stg_gsheets__inventory_inventory_id.329564dd49", "compiled": true, "compiled_code": "\n    \n    \n\nselect\n    inventory_id as unique_field,\n    count(*) as n_records\n\nfrom analytics.staging.stg_gsheets__inventory\nwhere inventory_id is not null\ngroup by inventory_id\nhaving count(*) > 1\n\n\n", "relation_name": null}, {"status": "success", "timing": [{"name": "compile", "started_at": "2024-07-07T14:02:19.550833Z", "completed_at": "2024-07-07T14:02:19.568908Z"}, {"name": "execute", "started_at": "2024-07-07T14:02:19.575729Z", "completed_at": "2024-07-07T14:02:19.575737Z"}], "thread_id": "Thread-2", "execution_time": 0.030194997787475586, "adapter_response": {}, "message": null, "failures": null, "unique_id": "test.wwi_analytics.relationships_stg_gsheets__inventory_film_id__film_id__ref_stg_gsheets__film_.abe5aa437f", "compiled": true, "compiled_code": "\n    \n    \n\nwith child as (\n    select film_id as from_field\n    from analytics.staging.stg_gsheets__inventory\n    where film_id is not null\n),\n\nparent as (\n    select film_id as to_field\n    from analytics.staging.stg_gsheets__film\n)\n\nselect\n    from_field\n\nfrom child\nleft join parent\n    on child.from_field = parent.to_field\n\nwhere parent.to_field is null\n\n\n", "relation_name": null}, {"status": "success", "timing": [{"name": "compile", "started_at": "2024-07-07T14:02:19.563702Z", "completed_at": "2024-07-07T14:02:19.575173Z"}, {"name": "execute", "started_at": "2024-07-07T14:02:19.578116Z", "completed_at": "2024-07-07T14:02:19.578124Z"}], "thread_id": "Thread-3", "execution_time": 0.028689146041870117, "adapter_response": {}, "message": null, "failures": null, "unique_id": "test.wwi_analytics.not_null_stg_gsheets__language_language_id.f0ab81b159", "compiled": true, "compiled_code": "\n    \n    \n\n\n\nselect language_id\nfrom analytics.staging.stg_gsheets__language\nwhere language_id is null\n\n\n", "relation_name": null}, {"status": "success", "timing": [{"name": "compile", "started_at": "2024-07-07T14:02:19.569595Z", "completed_at": "2024-07-07T14:02:19.577462Z"}, {"name": "execute", "started_at": "2024-07-07T14:02:19.580355Z", "completed_at": "2024-07-07T14:02:19.580362Z"}], "thread_id": "Thread-1", "execution_time": 0.03027653694152832, "adapter_response": {}, "message": null, "failures": null, "unique_id": "test.wwi_analytics.not_null_stg_gsheets__payment_payment_id.c1eec68400", "compiled": true, "compiled_code": "\n    \n    \n\n\n\nselect payment_id\nfrom analytics.staging.stg_gsheets__payment\nwhere payment_id is null\n\n\n", "relation_name": null}, {"status": "success", "timing": [{"name": "compile", "started_at": "2024-07-07T14:02:19.585128Z", "completed_at": "2024-07-07T14:02:19.598720Z"}, {"name": "execute", "started_at": "2024-07-07T14:02:19.609184Z", "completed_at": "2024-07-07T14:02:19.609196Z"}], "thread_id": "Thread-4", "execution_time": 0.02960991859436035, "adapter_response": {}, "message": null, "failures": null, "unique_id": "test.wwi_analytics.not_null_stg_gsheets__payment_staff_id.263865fc70", "compiled": true, "compiled_code": "\n    \n    \n\n\n\nselect staff_id\nfrom analytics.staging.stg_gsheets__payment\nwhere staff_id is null\n\n\n", "relation_name": null}, {"status": "success", "timing": [{"name": "compile", "started_at": "2024-07-07T14:02:19.591104Z", "completed_at": "2024-07-07T14:02:19.608597Z"}, {"name": "execute", "started_at": "2024-07-07T14:02:19.610381Z", "completed_at": "2024-07-07T14:02:19.610388Z"}], "thread_id": "Thread-2", "execution_time": 0.028511762619018555, "adapter_response": {}, "message": null, "failures": null, "unique_id": "test.wwi_analytics.relationships_stg_gsheets__payment_customer_id__customer_id__ref_stg_gsheets__customer_.7e3e02e6d3", "compiled": true, "compiled_code": "\n    \n    \n\nwith child as (\n    select customer_id as from_field\n    from analytics.staging.stg_gsheets__payment\n    where customer_id is not null\n),\n\nparent as (\n    select customer_id as to_field\n    from analytics.staging.stg_gsheets__customer\n)\n\nselect\n    from_field\n\nfrom child\nleft join parent\n    on child.from_field = parent.to_field\n\nwhere parent.to_field is null\n\n\n", "relation_name": null}, {"status": "success", "timing": [{"name": "compile", "started_at": "2024-07-07T14:02:19.599294Z", "completed_at": "2024-07-07T14:02:19.612059Z"}, {"name": "execute", "started_at": "2024-07-07T14:02:19.614704Z", "completed_at": "2024-07-07T14:02:19.614711Z"}], "thread_id": "Thread-3", "execution_time": 0.03091716766357422, "adapter_response": {}, "message": null, "failures": null, "unique_id": "test.wwi_analytics.unique_stg_gsheets__payment_payment_id.024366fcb6", "compiled": true, "compiled_code": "\n    \n    \n\nselect\n    payment_id as unique_field,\n    count(*) as n_records\n\nfrom analytics.staging.stg_gsheets__payment\nwhere payment_id is not null\ngroup by payment_id\nhaving count(*) > 1\n\n\n", "relation_name": null}, {"status": "success", "timing": [{"name": "compile", "started_at": "2024-07-07T14:02:19.603941Z", "completed_at": "2024-07-07T14:02:19.612740Z"}, {"name": "execute", "started_at": "2024-07-07T14:02:19.615593Z", "completed_at": "2024-07-07T14:02:19.615602Z"}], "thread_id": "Thread-1", "execution_time": 0.025901079177856445, "adapter_response": {}, "message": null, "failures": null, "unique_id": "test.wwi_analytics.not_null_stg_gsheets__rental_rental_id.912c348d75", "compiled": true, "compiled_code": "\n    \n    \n\n\n\nselect rental_id\nfrom analytics.staging.stg_gsheets__rental\nwhere rental_id is null\n\n\n", "relation_name": null}, {"status": "success", "timing": [{"name": "compile", "started_at": "2024-07-07T14:02:19.619781Z", "completed_at": "2024-07-07T14:02:19.633993Z"}, {"name": "execute", "started_at": "2024-07-07T14:02:19.646140Z", "completed_at": "2024-07-07T14:02:19.646154Z"}], "thread_id": "Thread-4", "execution_time": 0.03223896026611328, "adapter_response": {}, "message": null, "failures": null, "unique_id": "test.wwi_analytics.relationships_stg_gsheets__payment_rental_id__rental_id__ref_stg_gsheets__rental_.658b8f4c91", "compiled": true, "compiled_code": "\n    \n    \n\nwith child as (\n    select rental_id as from_field\n    from analytics.staging.stg_gsheets__payment\n    where rental_id is not null\n),\n\nparent as (\n    select rental_id as to_field\n    from analytics.staging.stg_gsheets__rental\n)\n\nselect\n    from_field\n\nfrom child\nleft join parent\n    on child.from_field = parent.to_field\n\nwhere parent.to_field is null\n\n\n", "relation_name": null}, {"status": "success", "timing": [{"name": "compile", "started_at": "2024-07-07T14:02:19.626813Z", "completed_at": "2024-07-07T14:02:19.640413Z"}, {"name": "execute", "started_at": "2024-07-07T14:02:19.647224Z", "completed_at": "2024-07-07T14:02:19.647233Z"}], "thread_id": "Thread-2", "execution_time": 0.030837059020996094, "adapter_response": {}, "message": null, "failures": null, "unique_id": "test.wwi_analytics.relationships_stg_gsheets__rental_inventory_id__inventory_id__ref_stg_gsheets__inventory_.3dc8924bea", "compiled": true, "compiled_code": "\n    \n    \n\nwith child as (\n    select inventory_id as from_field\n    from analytics.staging.stg_gsheets__rental\n    where inventory_id is not null\n),\n\nparent as (\n    select inventory_id as to_field\n    from analytics.staging.stg_gsheets__inventory\n)\n\nselect\n    from_field\n\nfrom child\nleft join parent\n    on child.from_field = parent.to_field\n\nwhere parent.to_field is null\n\n\n", "relation_name": null}, {"status": "success", "timing": [{"name": "compile", "started_at": "2024-07-07T14:02:19.634719Z", "completed_at": "2024-07-07T14:02:19.648150Z"}, {"name": "execute", "started_at": "2024-07-07T14:02:19.650941Z", "completed_at": "2024-07-07T14:02:19.650951Z"}], "thread_id": "Thread-3", "execution_time": 0.02558135986328125, "adapter_response": {}, "message": null, "failures": null, "unique_id": "test.wwi_analytics.unique_stg_gsheets__rental_rental_id.c44d87ccee", "compiled": true, "compiled_code": "\n    \n    \n\nselect\n    rental_id as unique_field,\n    count(*) as n_records\n\nfrom analytics.staging.stg_gsheets__rental\nwhere rental_id is not null\ngroup by rental_id\nhaving count(*) > 1\n\n\n", "relation_name": null}, {"status": "success", "timing": [{"name": "compile", "started_at": "2024-07-07T14:02:19.641037Z", "completed_at": "2024-07-07T14:02:19.650315Z"}, {"name": "execute", "started_at": "2024-07-07T14:02:19.653136Z", "completed_at": "2024-07-07T14:02:19.653143Z"}], "thread_id": "Thread-1", "execution_time": 0.027115583419799805, "adapter_response": {}, "message": null, "failures": null, "unique_id": "model.wwi_analytics.dim_rental", "compiled": true, "compiled_code": "with\n\nrental as (\n  select * from analytics.staging.stg_gsheets__rental\n),\n\ninventory as (\n  select * from analytics.staging.stg_gsheets__inventory\n), \n\ncustomer as (\n  select * from analytics.staging.stg_gsheets__customer\n),\n\nstaff as (\n  select * from analytics.staging.stg_gsheets__staff\n),\n\nfinal as (\n  select\n    md5(cast(coalesce(cast(rental.rental_id as TEXT), '_dbt_utils_surrogate_key_null_') as TEXT)) as rental_key,\n\n    rental.rental_id,\n    rental.staff_id,\n    staff.staff_fullname,\n    rental.customer_id,\n    customer.customer_name,\n    rental.rental_date,\n    rental.return_date,\n    rental.inventory_id,\n    inventory.film_id\n\n  from rental\n\n  left join staff \n    on rental.staff_id = staff.staff_id\n  left join customer \n    on rental.customer_id = customer.customer_id\n  left join inventory \n    on rental.inventory_id = inventory.inventory_id\n)\n\nselect * from final", "relation_name": "analytics.warehouse.dim_rental"}, {"status": "success", "timing": [{"name": "compile", "started_at": "2024-07-07T14:02:19.657341Z", "completed_at": "2024-07-07T14:02:19.668971Z"}, {"name": "execute", "started_at": "2024-07-07T14:02:19.675336Z", "completed_at": "2024-07-07T14:02:19.675344Z"}], "thread_id": "Thread-4", "execution_time": 0.023603200912475586, "adapter_response": {}, "message": null, "failures": null, "unique_id": "test.wwi_analytics.not_null_stg_gsheets__staff_staff_id.92234d01cc", "compiled": true, "compiled_code": "\n    \n    \n\n\n\nselect staff_id\nfrom analytics.staging.stg_gsheets__staff\nwhere staff_id is null\n\n\n", "relation_name": null}, {"status": "success", "timing": [{"name": "compile", "started_at": "2024-07-07T14:02:19.661868Z", "completed_at": "2024-07-07T14:02:19.670292Z"}, {"name": "execute", "started_at": "2024-07-07T14:02:19.682299Z", "completed_at": "2024-07-07T14:02:19.682308Z"}], "thread_id": "Thread-2", "execution_time": 0.02992081642150879, "adapter_response": {}, "message": null, "failures": null, "unique_id": "test.wwi_analytics.relationships_stg_gsheets__staff_address_id__address_id__ref_stg_gsheets__address_.321fdea53d", "compiled": true, "compiled_code": "\n    \n    \n\nwith child as (\n    select address_id as from_field\n    from analytics.staging.stg_gsheets__staff\n    where address_id is not null\n),\n\nparent as (\n    select address_id as to_field\n    from analytics.staging.stg_gsheets__address\n)\n\nselect\n    from_field\n\nfrom child\nleft join parent\n    on child.from_field = parent.to_field\n\nwhere parent.to_field is null\n\n\n", "relation_name": null}, {"status": "success", "timing": [{"name": "compile", "started_at": "2024-07-07T14:02:19.670886Z", "completed_at": "2024-07-07T14:02:19.684271Z"}, {"name": "execute", "started_at": "2024-07-07T14:02:19.686876Z", "completed_at": "2024-07-07T14:02:19.686884Z"}], "thread_id": "Thread-3", "execution_time": 0.030313968658447266, "adapter_response": {}, "message": null, "failures": null, "unique_id": "test.wwi_analytics.unique_stg_gsheets__staff_staff_id.7926c02e8d", "compiled": true, "compiled_code": "\n    \n    \n\nselect\n    staff_id as unique_field,\n    count(*) as n_records\n\nfrom analytics.staging.stg_gsheets__staff\nwhere staff_id is not null\ngroup by staff_id\nhaving count(*) > 1\n\n\n", "relation_name": null}, {"status": "success", "timing": [{"name": "compile", "started_at": "2024-07-07T14:02:19.676260Z", "completed_at": "2024-07-07T14:02:19.685543Z"}, {"name": "execute", "started_at": "2024-07-07T14:02:19.688427Z", "completed_at": "2024-07-07T14:02:19.688434Z"}], "thread_id": "Thread-1", "execution_time": 0.020948171615600586, "adapter_response": {}, "message": null, "failures": null, "unique_id": "model.wwi_analytics.dim_staff", "compiled": true, "compiled_code": "with\n\nstaff as (\n  select * from analytics.staging.stg_gsheets__staff\n),\n\naddress as (\n  select * from analytics.staging.stg_gsheets__address\n),\n\nstore as (\n  select * from analytics.staging.stg_gsheets__store\n),\n\nfinal as (\n\n  select\n    md5(cast(coalesce(cast(staff.staff_id as TEXT), '_dbt_utils_surrogate_key_null_') as TEXT)) as staff_key,\n\n    staff.staff_id,\n    staff.email,\n    staff.password,\n    staff.staff_fullname,\n    staff.username,\n    \n    staff_address.address as staff_address,\n    store_address.address as store_address\n\n  from staff\n\n  left join address as staff_address \n    on staff.address_id = staff_address.address_id\n  left join store \n    on staff.store_id = store.store_id\n  left join address as store_address \n    on store.address_id = store_address.address_id\n\n)\n\nselect * from final", "relation_name": "analytics.warehouse.dim_staff"}, {"status": "success", "timing": [{"name": "compile", "started_at": "2024-07-07T14:02:19.692002Z", "completed_at": "2024-07-07T14:02:19.704469Z"}, {"name": "execute", "started_at": "2024-07-07T14:02:19.710285Z", "completed_at": "2024-07-07T14:02:19.710294Z"}], "thread_id": "Thread-4", "execution_time": 0.024237394332885742, "adapter_response": {}, "message": null, "failures": null, "unique_id": "test.wwi_analytics.not_null_stg_gsheets__store_store_id.4b0ea577c8", "compiled": true, "compiled_code": "\n    \n    \n\n\n\nselect store_id\nfrom analytics.staging.stg_gsheets__store\nwhere store_id is null\n\n\n", "relation_name": null}, {"status": "success", "timing": [{"name": "compile", "started_at": "2024-07-07T14:02:19.697393Z", "completed_at": "2024-07-07T14:02:19.711156Z"}, {"name": "execute", "started_at": "2024-07-07T14:02:19.718782Z", "completed_at": "2024-07-07T14:02:19.718791Z"}], "thread_id": "Thread-2", "execution_time": 0.031110763549804688, "adapter_response": {}, "message": null, "failures": null, "unique_id": "test.wwi_analytics.relationships_stg_gsheets__store_address_id__address_id__ref_stg_gsheets__address_.a1f727ef90", "compiled": true, "compiled_code": "\n    \n    \n\nwith child as (\n    select address_id as from_field\n    from analytics.staging.stg_gsheets__store\n    where address_id is not null\n),\n\nparent as (\n    select address_id as to_field\n    from analytics.staging.stg_gsheets__address\n)\n\nselect\n    from_field\n\nfrom child\nleft join parent\n    on child.from_field = parent.to_field\n\nwhere parent.to_field is null\n\n\n", "relation_name": null}, {"status": "success", "timing": [{"name": "compile", "started_at": "2024-07-07T14:02:19.705817Z", "completed_at": "2024-07-07T14:02:19.718199Z"}, {"name": "execute", "started_at": "2024-07-07T14:02:19.719801Z", "completed_at": "2024-07-07T14:02:19.719807Z"}], "thread_id": "Thread-3", "execution_time": 0.023352384567260742, "adapter_response": {}, "message": null, "failures": null, "unique_id": "test.wwi_analytics.unique_stg_gsheets__store_store_id.1d1ab570b3", "compiled": true, "compiled_code": "\n    \n    \n\nselect\n    store_id as unique_field,\n    count(*) as n_records\n\nfrom analytics.staging.stg_gsheets__store\nwhere store_id is not null\ngroup by store_id\nhaving count(*) > 1\n\n\n", "relation_name": null}, {"status": "success", "timing": [{"name": "compile", "started_at": "2024-07-07T14:02:19.711770Z", "completed_at": "2024-07-07T14:02:19.720984Z"}, {"name": "execute", "started_at": "2024-07-07T14:02:19.721593Z", "completed_at": "2024-07-07T14:02:19.721599Z"}], "thread_id": "Thread-1", "execution_time": 0.018630027770996094, "adapter_response": {}, "message": null, "failures": null, "unique_id": "model.wwi_analytics.fct_payment", "compiled": true, "compiled_code": "with\n\npayment as (\n  select * from analytics.staging.stg_gsheets__payment\n),\n\nstaff as (\n  select * from analytics.warehouse.dim_staff\n),\n\nrental as (\n  select * from analytics.warehouse.dim_rental\n),\n\ncustomer as (\n  select * from analytics.warehouse.dim_customer\n),\n\nfinal as (\n\n  select \n    md5(cast(coalesce(cast(payment.payment_id as TEXT), '_dbt_utils_surrogate_key_null_') as TEXT)) as payment_key,\n\n    staff.staff_key,\n    rental.rental_key,\n    customer.customer_key,\n    amount,\n    payment_date\n\n  from payment\n\n  left join staff \n    on payment.staff_id = staff.staff_id\n  left join rental \n    on payment.rental_id = rental.rental_id\n  left join customer \n    on payment.customer_id = customer.customer_id\n)\n\nselect * from final", "relation_name": "analytics.warehouse.fct_payment"}, {"status": "success", "timing": [{"name": "compile", "started_at": "2024-07-07T14:02:19.725869Z", "completed_at": "2024-07-07T14:02:19.732651Z"}, {"name": "execute", "started_at": "2024-07-07T14:02:19.738691Z", "completed_at": "2024-07-07T14:02:19.738702Z"}], "thread_id": "Thread-4", "execution_time": 0.015309572219848633, "adapter_response": {}, "message": null, "failures": null, "unique_id": "model.wwi_analytics.payment_by_rental", "compiled": true, "compiled_code": "with \n\nfct_payment as (\n  select * from analytics.warehouse.fct_payment\n),\n\nfinal as (\n\n  select\n    fct_payment.rental_key,\n\n    sum(amount) as total_amount,\n    avg(amount) as average_amount,\n    min(amount) as minimum_amount,\n    max(amount) as maximum_amount,\n    count(rental_key) as total_payments\n\n  from fct_payment\n  group by rental_key\n)\n\nselect * from final", "relation_name": "analytics.marts.payment_by_rental"}, {"status": "success", "timing": [{"name": "compile", "started_at": "2024-07-07T14:02:19.734481Z", "completed_at": "2024-07-07T14:02:19.749362Z"}, {"name": "execute", "started_at": "2024-07-07T14:02:19.750160Z", "completed_at": "2024-07-07T14:02:19.750168Z"}], "thread_id": "Thread-2", "execution_time": 0.02029728889465332, "adapter_response": {}, "message": null, "failures": null, "unique_id": "model.wwi_analytics.payment_summary", "compiled": true, "compiled_code": "with\n\nfct_payment as (\n  select * from analytics.warehouse.fct_payment\n),\n\ndim_staff as (\n  select * from analytics.warehouse.dim_staff\n),\n\ndim_rental as (\n  select * from analytics.warehouse.dim_rental\n),\n\ndim_customer as (\n  select * from analytics.warehouse.dim_customer\n),\n\nfinal as (\n\n  select\n    fct_payment.payment_key,\n    dim_rental.rental_key,\n\n    dim_customer.customer_name,\n    dim_customer.customer_email,\n    dim_customer.customer_is_active,\n    dim_customer.address as customer_address,\n    dim_customer.postal_code,\n    dim_customer.address_number,\n    dim_customer.district,\n    dim_customer.city,\n    dim_customer.country,\n  \n    dim_staff.staff_fullname,\n    dim_staff.username,\n    dim_staff.email,\n    dim_staff.password,\n    dim_staff.staff_address,\n    dim_staff.store_address,\n\n    dim_rental.rental_date,\n    dim_rental.return_date,\n    dim_rental.film_id,\n\n    fct_payment.amount,\n    fct_payment.payment_date\n\n  from fct_payment\n\n  left join dim_customer\n    on fct_payment.customer_key = dim_customer.customer_key\n  left join dim_staff\n    on fct_payment.staff_key = dim_staff.staff_key\n  left join dim_rental\n    on fct_payment.rental_key = dim_rental.rental_key\n)\n\nselect * from final", "relation_name": "analytics.marts.payment_summary"}, {"status": "success", "timing": [{"name": "compile", "started_at": "2024-07-07T14:02:19.744217Z", "completed_at": "2024-07-07T14:02:19.751258Z"}, {"name": "execute", "started_at": "2024-07-07T14:02:19.751890Z", "completed_at": "2024-07-07T14:02:19.751897Z"}], "thread_id": "Thread-1", "execution_time": 0.020592689514160156, "adapter_response": {}, "message": null, "failures": null, "unique_id": "test.wwi_analytics.unique_fct_payment_payment_key.bd328b07cb", "compiled": true, "compiled_code": "\n    \n    \n\nselect\n    payment_key as unique_field,\n    count(*) as n_records\n\nfrom analytics.warehouse.fct_payment\nwhere payment_key is not null\ngroup by payment_key\nhaving count(*) > 1\n\n\n", "relation_name": null}, {"status": "success", "timing": [{"name": "compile", "started_at": "2024-07-07T14:02:19.739603Z", "completed_at": "2024-07-07T14:02:19.752884Z"}, {"name": "execute", "started_at": "2024-07-07T14:02:19.753505Z", "completed_at": "2024-07-07T14:02:19.753511Z"}], "thread_id": "Thread-3", "execution_time": 0.022974252700805664, "adapter_response": {}, "message": null, "failures": null, "unique_id": "test.wwi_analytics.not_null_fct_payment_payment_key.dd0ceca2c8", "compiled": true, "compiled_code": "\n    \n    \n\n\n\nselect payment_key\nfrom analytics.warehouse.fct_payment\nwhere payment_key is null\n\n\n", "relation_name": null}], "elapsed_time": 2.743940830230713, "args": {"cache_selected_only": false, "populate_cache": true, "profiles_dir": ".", "version_check": true, "log_format_file": "debug", "log_path": "/home/runner/work/project01_dbt_snowflake/project01_dbt_snowflake/logs", "log_file_max_bytes": 10485760, "static_parser": true, "indirect_selection": "eager", "invocation_command": "dbt docs generate --profiles-dir . --target prod", "send_anonymous_usage_stats": true, "use_colors": true, "source_freshness_run_project_hooks": false, "partial_parse_file_diff": true, "defer": false, "introspect": true, "partial_parse": true, "warn_error_options": {"include": [], "exclude": []}, "require_resource_names_without_spaces": false, "favor_state": false, "select": [], "strict_mode": false, "log_format": "default", "vars": {}, "require_explicit_package_overrides_for_builtin_materializations": true, "which": "generate", "quiet": false, "empty_catalog": false, "write_json": true, "macro_debugging": false, "project_dir": "/home/runner/work/project01_dbt_snowflake/project01_dbt_snowflake", "use_colors_file": true, "log_level_file": "debug", "show_resource_report": false, "exclude": [], "print": true, "static": false, "compile": true, "target": "prod", "printer_width": 80, "enable_legacy_logger": false, "log_level": "info"}}